{"2006":{"totalPopulation":"2640.0","totalCitizen":"2454.0","totalRegistered":"1650.0","totalVoted":"1220.0","hispanicPopulation":"258.0","hispanicCitizen":"192.0","hispanicRegistered":"90.0","hispanicVoted":"49.0","percentHispanicPopulation":"0.09772727272727273","percentHispanicRegistered":"0.05454545454545454","percentHispanicVoted":"0.04016393442622951"},"2008":{"totalPopulation":"2651.0","totalCitizen":"2396.0","totalRegistered":"1761.0","totalVoted":"1610.0","hispanicPopulation":"253.0","hispanicCitizen":"191.0","hispanicRegistered":"104.0","hispanicVoted":"89.0","percentHispanicPopulation":"0.0954356846473029","percentHispanicRegistered":"0.059057353776263484","percentHispanicVoted":"0.055279503105590065"},"2010":{"totalPopulation":"2648.0","totalCitizen":"2463.0","totalRegistered":"1641.0","totalVoted":"1215.0","hispanicPopulation":"243.0","hispanicCitizen":"197.0","hispanicRegistered":"111.0","hispanicVoted":"56.0","percentHispanicPopulation":"0.09176737160120846","percentHispanicRegistered":"0.06764168190127971","percentHispanicVoted":"0.04609053497942387"},"2012":{"totalPopulation":"2726.0","totalCitizen":"2499.0","totalRegistered":"1760.0","totalVoted":"1568.0","hispanicPopulation":"292.0","hispanicCitizen":"220.0","hispanicRegistered":"127.0","hispanicVoted":"103.0","percentHispanicPopulation":"0.10711665443873808","percentHispanicRegistered":"0.07215909090909091","percentHispanicVoted":"0.06568877551020408"}}